datacompy_report/DatacompyReport.py
datacompy_report/__init__.py
datacompy_report/_modidx.py
datacompy_report-0.0.2.dist-info/LICENSE
datacompy_report-0.0.2.dist-info/METADATA
datacompy_report-0.0.2.dist-info/WHEEL
datacompy_report-0.0.2.dist-info/entry_points.txt
datacompy_report-0.0.2.dist-info/top_level.txt
datacompy_report-0.0.2.dist-info/RECORD
