Metadata-Version: 2.1
Name: datacompy-report
Version: 0.0.2
Summary: Create reports allowing for comparing two DataFrames.
Home-page: https://github.com/nagol/datacompy_report
Author: Logan Lossing
Author-email: loganlossing@gmail.com
License: Apache Software License 2.0
Keywords: nbdev jupyter notebook python
Classifier: Development Status :: 4 - Beta
Classifier: Intended Audience :: Developers
Classifier: Natural Language :: English
Classifier: Programming Language :: Python :: 3.7
Classifier: Programming Language :: Python :: 3.8
Classifier: Programming Language :: Python :: 3.9
Classifier: Programming Language :: Python :: 3.10
Classifier: License :: OSI Approved :: Apache Software License
Requires-Python: >=3.7
License-File: LICENSE
Requires-Dist: fastcore
Requires-Dist: pandas
Requires-Dist: datacompy
Requires-Dist: xlsxwriter
Provides-Extra: dev
Requires-Dist: fastcore ; extra == 'dev'
Requires-Dist: pandas ; extra == 'dev'
Requires-Dist: datacompy ; extra == 'dev'
Requires-Dist: xlsxwriter ; extra == 'dev'
